activitystreams2/__init__.py
activitystreams2-0.5.0.dist-info/DESCRIPTION.rst
activitystreams2-0.5.0.dist-info/METADATA
activitystreams2-0.5.0.dist-info/RECORD
activitystreams2-0.5.0.dist-info/WHEEL
activitystreams2-0.5.0.dist-info/metadata.json
activitystreams2-0.5.0.dist-info/top_level.txt
aspy/__init__.py
