Metadata-Version: 2.0
Name: activitystreams2
Version: 0.5.0
Summary: An activity streams 2 library
Home-page: https://gitlab.com/alantrick/activitystreams2
Author: Alan Trick
Author-email: me@alantrick.ca
License: LGPL3+
Project-URL: Bug Tracker, https://gitlab.com/alantrick/activitystreams2/issues
Project-URL: Documentation, https://alantrick.gitlab.io/activitystreams2
Project-URL: Source Code, https://gitlab.com/alantrick/activitystreams2
Keywords: activity-feed,activity-streams,social
Platform: UNKNOWN
Classifier: Development Status :: 2 - Pre-Alpha
Classifier: Environment :: Web Environment
Classifier: Intended Audience :: Developers
Classifier: License :: OSI Approved :: GNU Lesser General Public License v3 or later (LGPLv3+)
Classifier: Operating System :: OS Independent
Classifier: Programming Language :: Python
Classifier: Programming Language :: Python :: 3.6
Classifier: Topic :: Utilities
Requires-Python: >=3.6
Provides-Extra: test
Provides-Extra: docs
Requires-Dist: isodate
Provides-Extra: docs
Requires-Dist: sphinx; extra == 'docs'
Requires-Dist: sphinx-rtd-theme; extra == 'docs'
Provides-Extra: test
Requires-Dist: pytest; extra == 'test'
Requires-Dist: pytest-cov; extra == 'test'
Requires-Dist: pytest-pythonpath; extra == 'test'
Requires-Dist: tox; extra == 'test'
